[{"state":"Work in Progress","number":"INC0433830","sys_created_on":"2018-08-20 08:18:19","sys_created_by":"fvazquez","caller_id":"Kelly Chu","category":"Access/Connectivity","subcategory":"Connectivity","u_detail":"Router","priority":"4 - Medium","assignment_group":"TCS - Desktop Integration Team","assigned_to":"Alex Alvarez","location":"NY-HY: 12th Floor","contact_type":"Phone","caller_id.u_brand_affiliation":"Coach","made_sla":"true","short_description":"User is having issues with network connection on docking station /ethernet (Forescout/coutneract issue)"},{"state":"Work in Progress","number":"INC0433830","sys_created_on":"2018-08-20 08:18:19","sys_created_by":"fvazquez","caller_id":"Kelly Chu","category":"Access/Connectivity","subcategory":"Connectivity","u_detail":"Router","priority":"4 - Medium","assignment_group":"TCS - Desktop Integration Team","assigned_to":"Alex Alvarez","location":"NY-HY: 12th Floor","contact_type":"Phone","caller_id.u_brand_affiliation":"Coach","made_sla":"true","short_description":"User is having issues with network connection on docking station /ethernet (Forescout/coutneract issue)"},{"state":"Work in Progress","number":"INC0433830","sys_created_on":"2018-08-20 08:18:19","sys_created_by":"fvazquez","caller_id":"Kelly Chu","category":"Access/Connectivity","subcategory":"Connectivity","u_detail":"Router","priority":"4 - Medium","assignment_group":"TCS - Desktop Integration Team","assigned_to":"Alex Alvarez","location":"NY-HY: 12th Floor","contact_type":"Phone","caller_id.u_brand_affiliation":"Coach","made_sla":"true","short_description":"User is having issues with network connection on docking station /ethernet (Forescout/coutneract issue)"},{"state":"Work in Progress","number":"INC0433830","sys_created_on":"2018-08-20 08:18:19","sys_created_by":"fvazquez","caller_id":"Kelly Chu","category":"Access/Connectivity","subcategory":"Connectivity","u_detail":"Router","priority":"4 - Medium","assignment_group":"TCS - Desktop Integration Team","assigned_to":"Alex Alvarez","location":"NY-HY: 12th Floor","contact_type":"Phone","caller_id.u_brand_affiliation":"Coach","made_sla":"true","short_description":"User is having issues with network connection on docking station /ethernet (Forescout/coutneract issue)"},{"state":"Work in Progress","number":"INC0433830","sys_created_on":"2018-08-20 08:18:19","sys_created_by":"fvazquez","caller_id":"Kelly Chu","category":"Access/Connectivity","subcategory":"Connectivity","u_detail":"Router","priority":"4 - Medium","assignment_group":"TCS - Desktop Integration Team","assigned_to":"Alex Alvarez","location":"NY-HY: 12th Floor","contact_type":"Phone","caller_id.u_brand_affiliation":"Coach","made_sla":"true","short_description":"User is having issues with network connection on docking station /ethernet (Forescout/coutneract issue)"},{"state":"Work in Progress","number":"INC0433830","sys_created_on":"2018-08-20 08:18:19","sys_created_by":"fvazquez","caller_id":"Kelly Chu","category":"Access/Connectivity","subcategory":"Connectivity","u_detail":"Router","priority":"4 - Medium","assignment_group":"TCS - Desktop Integration Team","assigned_to":"Alex Alvarez","location":"NY-HY: 12th Floor","contact_type":"Phone","caller_id.u_brand_affiliation":"Coach","made_sla":"true","short_description":"User is having issues with network connection on docking station /ethernet (Forescout/coutneract issue)"},{"state":"Work in Progress","number":"INC0433830","sys_created_on":"2018-08-20 08:18:19","sys_created_by":"fvazquez","caller_id":"Kelly Chu","category":"Access/Connectivity","subcategory":"Connectivity","u_detail":"Router","priority":"4 - Medium","assignment_group":"TCS - Desktop Integration Team","assigned_to":"Alex Alvarez","location":"NY-HY: 12th Floor","contact_type":"Phone","caller_id.u_brand_affiliation":"Coach","made_sla":"true","short_description":"User is having issues with network connection on docking station /ethernet (Forescout/coutneract issue)"}]